{
  "$schema" : "http://json-schema.org/draft-04/schema#",
  "id" : "Haushalt",
  "type" : "object",
  "javaType" : "de.europace.kreditsmart.api.import.haushalt.Haushalt",
  "properties" : {
    "kontoverbindung" : {
      "type" : "object",
      "javaType" : "de.europace.kreditsmart.api.import.haushalt.Kontoverbindung",
      "$ref" : "Kontoverbindung.json"
    },
    "verbindlichkeiten" : {
      "type" : "object",
      "javaType" : "de.europace.kreditsmart.api.import.haushalt.verbindlichkeiten.Verbindlichkeiten",
      "$ref" : "Verbindlichkeiten.json"
    },
    "vermoegen" : {
      "type" : "object",
      "javaType" : "de.europace.kreditsmart.api.import.haushalt.vermoegen.Vermoegen",
      "$ref" : "Vermoegen.json"
    },
    "immobilien" : {
      "type" : "array",
      "items" : {
        "type" : "object",
        "javaType" : "de.europace.kreditsmart.api.import.haushalt.Immobilie",
        "$ref" : "Immobilie.json"
      }
    },
    "ausgaben" : {
      "type" : "object",
      "javaType" : "de.europace.kreditsmart.api.import.haushalt.ausgaben.Ausgaben",
      "$ref" : "Ausgaben.json"
    },
    "einnahmen" : {
      "type" : "object",
      "javaType" : "de.europace.kreditsmart.api.import.haushalt.einnahmen.Einnahmen",
      "$ref" : "Einnahmen.json"
    },
    "kinder" : {
      "type" : "array",
      "items" : {
        "type" : "object",
        "javaType" : "de.europace.kreditsmart.api.import.haushalt.Kind",
        "$ref" : "Kind.json"
      }
    }
  }
}